giter/__init__.py
giter-0.0.2.dist-info/LICENSE
giter-0.0.2.dist-info/METADATA
giter-0.0.2.dist-info/WHEEL
giter-0.0.2.dist-info/top_level.txt
giter-0.0.2.dist-info/RECORD
